{
  "name": "Ronald Andrews",
  "age": 22,
  "address": {
    "street": "Dakuw Avenue",
    "city": "Racfusuv",
    "state": "IN",
    "zip": "05069"
  },
  "contact": {
    "phone": "(450) 975-2981",
    "servicePhone": "800162993"
  },
  "birthday": "1981-05-27T22:54:36.872Z",
  "ip": "56.238.68.13",
  "foo": "bar",
  "profile": {
    "about": "Jifufu umulu lip ozuzowmal simagud foguge apesu bukfo uwibas udo pewoku kozi el meuj panpu evlet vo. Ur ik unzitef elu du hiisigi kuw balifa urimulo vecmerrok piwcomup ofgenog powra ge ra. Fiduj me ufepraw pob ji gozregov nuccan zi cif ig hovpa iviiketa ugeka romen zi. Id simed ta vod vodeka ripge ev fec ukewavzul in boivabef wibijak wejka ehi ziokcir nobewedu jiusa. Gilibor ulitum jocicmug cupi ile fomobe zik berimu kori agcu ibu jo dihe. Kanwa oziabpi veostab zaf mu pu wifze mi nekego nopwujnew vefar lisaneh mukohtun wa hordi ese damisumu.",
    "bio": "Darmad mi sig la umpifej ififa basohani itnamwuj wam tuczu be pef jo damocva. Tog tifabumu pafri bumavoj notrumba nit elaga gam ro fuf gicubu puz. Feredlad imesi cawus fufivhi gecfib tuv kedjejif socpi caekaac hujokce lukgin nakhuag tibalo solwif vobowo. Houdaban be dazurak ra sian owrutbum uvuziwlaj novwutked cewjekgit emnefku fi pu laf cofzu wete kihjek keroc. Zaajval bevonupo gofciz rojimo vu keze wav ruwigel jarilvo ipheffuf furmo kobe kacepa po."
  },
  "apiKey": "17e3540e4e4f2adc88d6233558307d5b1f9bc48b72e32f40a76be37ae8f087d8",
  "currency": {
    "code": "MMK",
    "name": "Myanmar (Burma) Kyat"
  }
}